rand_wordpair/__init__.py
rand_wordpair/__main__.py
rand_wordpair/gen.py
rand_wordpair-0.0.1.dist-info/LICENSE
rand_wordpair-0.0.1.dist-info/METADATA
rand_wordpair-0.0.1.dist-info/WHEEL
rand_wordpair-0.0.1.dist-info/top_level.txt
rand_wordpair-0.0.1.dist-info/RECORD
