Metadata-Version: 2.1
Name: rand_wordpair
Version: 0.0.1
Summary: Python module to generate a random pair of English words
Author-email: Dan Roche <roche@usna.edu>
Project-URL: Homepage, https://github.com/dsroche/rand_wordpair
Requires-Python: >=3.10
License-File: LICENSE
Requires-Dist: nltk
